AUTHORS.rst
CONTRIBUTING.rst
HISTORY.rst
LICENSE
MANIFEST.in
README.rst
setup.cfg
setup.py
dictframe/__init__.py
dictframe/cli.py
dictframe/dictframe.py
dictframe.egg-info/PKG-INFO
dictframe.egg-info/SOURCES.txt
dictframe.egg-info/dependency_links.txt
dictframe.egg-info/entry_points.txt
dictframe.egg-info/not-zip-safe
dictframe.egg-info/requires.txt
dictframe.egg-info/top_level.txt
docs/Makefile
docs/authors.rst
docs/conf.py
docs/contributing.rst
docs/history.rst
docs/index.rst
docs/installation.rst
docs/make.bat
docs/readme.rst
docs/usage.rst
tests/test_dictframe.py