Metadata-Version: 1.1
Name: dictframe
Version: 0.1.0
Summary: none
Home-page: https://github.com/huntzhan/dictframe
Author: Hunt Zhan
Author-email: programmer.zhx@gmail.com
License: MIT license
Keywords: dictframe
Platform: UNKNOWN
Classifier: Development Status :: 2 - Pre-Alpha
Classifier: Intended Audience :: Developers
Classifier: License :: OSI Approved :: MIT License
Classifier: Natural Language :: English
Classifier: Programming Language :: Python :: 2
Classifier: Programming Language :: Python :: 2.7
Classifier: Programming Language :: Python :: 3
Classifier: Programming Language :: Python :: 3.4
Classifier: Programming Language :: Python :: 3.5
Classifier: Programming Language :: Python :: 3.6
